Metadata-Version: 2.1
Name: Basic-Calculater
Version: 1.0.0
Summary: A calculator
Home-page: UNKNOWN
Author: Atharv Rana
Author-email: mr.cheesy019@gmail.com
License: IIT
Keywords: calculator
Platform: UNKNOWN
Classifier: Development Status :: 5 - Production/Stable
Classifier: Intended Audience :: Education
Classifier: Operating System :: Microsoft :: Windows :: Windows 10
Classifier: License :: OSI Approved :: MIT License
Classifier: Programming Language :: Python :: 3
License-File: LICENCE.txt
